filapp/__init__.py
filapp/api.py
filapp-0.0.1.dist-info/LICENSE
filapp-0.0.1.dist-info/METADATA
filapp-0.0.1.dist-info/WHEEL
filapp-0.0.1.dist-info/top_level.txt
filapp-0.0.1.dist-info/RECORD
