Metadata-Version: 2.1
Name: filapp
Version: 0.0.1
Summary: Filapp API Client
Home-page: https://www.filapp.co
Author: Juan F. Duque
Author-email: jfelipe@grupodyd.com
License: MIT
Project-URL: Source, https://github.com/grupodyd/python-filapp
Project-URL: Tracker, https://github.com/grupodyd/python-filapp/issues
Keywords: filapp
Classifier: Development Status :: 2 - Pre-Alpha
Classifier: Environment :: Console
Classifier: Intended Audience :: Developers
Classifier: License :: OSI Approved :: MIT License
Classifier: Operating System :: OS Independent
Classifier: Programming Language :: Python
Classifier: Programming Language :: Python :: 3
Classifier: Programming Language :: Python :: 3 :: Only
Classifier: Programming Language :: Python :: 3.8
Classifier: Programming Language :: Python :: 3.9
Classifier: Programming Language :: Python :: 3.10
Classifier: Programming Language :: Python :: 3.11
Classifier: Programming Language :: Python :: 3.12
Classifier: Programming Language :: Python :: Implementation :: CPython
Classifier: Topic :: Software Development :: Libraries :: Python Modules
Requires-Python: >=3.8.0
License-File: LICENSE
Requires-Dist: httpx[http2] <1,>=0.24.0
Requires-Dist: pydantic <3,>=2
